mistql/__init__.py
mistql/builtins.py
mistql/cli.py
mistql/exceptions.py
mistql/execute.py
mistql/expression.py
mistql/gardenwall.py
mistql/grammar.lark
mistql/instance.py
mistql/parse.py
mistql/query.py
mistql/runtime_value.py
mistql/stack.py
mistql-0.4.12.dist-info/METADATA
mistql-0.4.12.dist-info/WHEEL
mistql-0.4.12.dist-info/entry_points.txt
mistql-0.4.12.dist-info/RECORD
