Metadata-Version: 2.1
Name: mistql
Version: 0.4.12
Summary: Python implementation of MistQL query language
Author: Evin Sellin
Author-email: evinism@gmail.com
Requires-Python: >=3.8.1,<4.0.0
Classifier: Programming Language :: Python :: 3
Classifier: Programming Language :: Python :: 3.9
Classifier: Programming Language :: Python :: 3.10
Classifier: Programming Language :: Python :: 3.11
Classifier: Programming Language :: Python :: 3.12
Requires-Dist: json-lines (>=0.5.0,<0.6.0)
Requires-Dist: lark (>=1.0.0,<2.0.0)
Requires-Dist: typeguard (>=2.13.3,<5.0.0)
Project-URL: issues, https://github.com/evinism/mistql/issues
